metadata/__init__.py
metadata/election.py
metadata/request.py
metadata/version.py
openelections_metadata-0.1.1.dist-info/DESCRIPTION.rst
openelections_metadata-0.1.1.dist-info/METADATA
openelections_metadata-0.1.1.dist-info/RECORD
openelections_metadata-0.1.1.dist-info/WHEEL
openelections_metadata-0.1.1.dist-info/metadata.json
openelections_metadata-0.1.1.dist-info/pbr.json
openelections_metadata-0.1.1.dist-info/top_level.txt
