Metadata-Version: 2.0
Name: openelections-metadata
Version: 0.1.1
Summary: A Python API wrapper for the OpenElections metadata API.
Home-page: http://openelections.net
Author: OpenElections
Author-email: openelections@gmail.com
License: UNKNOWN
Keywords: elections,metadata,api
Platform: UNKNOWN
Classifier: Development Status :: 3 - Alpha
Classifier: License :: OSI Approved :: MIT License
Classifier: Operating System :: OS Independent
Classifier: Programming Language :: Python
Classifier: Programming Language :: Python :: 2
Classifier: Programming Language :: Python :: 2.7
Classifier: Programming Language :: Python :: 3
Classifier: Programming Language :: Python :: 3.4
Classifier: Topic :: Internet
Classifier: Topic :: Internet :: WWW/HTTP
Classifier: Topic :: Text Processing
Classifier: Topic :: Text Processing :: Markup :: XML
Requires-Dist: python-dateutil
Requires-Dist: requests
Requires-Dist: six
